{
  "version": "1",
  "cognitoConfig": {
    "identityPoolName": "testAuthIdentityPool",
    "allowUnauthenticatedIdentities": false,
    "resourceNameTruncated": "huppo3c2a37cc",
    "userPoolName": "huppo",
    "autoVerifiedAttributes": [
      "email"
    ],
    "mfaConfiguration": "OFF",
    "mfaTypes": [
      "SMS Text Message"
    ],
    "smsAuthenticationMessage": "Your authentication code is {####}",
    "smsVerificationMessage": "Your verification code is {####}",
    "emailVerificationSubject": "Welcome to the Bloat!",
    "emailVerificationMessage": "Thank you for creating an account on Huppo. Your verification code is below.\n\nIf you did not request this code, this email can be safely ignored.\n\nVerification code: {####}",
    "defaultPasswordPolicy": false,
    "passwordPolicyMinLength": 6,
    "passwordPolicyCharacters": [],
    "requiredAttributes": [],
    "aliasAttributes": [],
    "userpoolClientGenerateSecret": false,
    "userpoolClientRefreshTokenValidity": 30,
    "userpoolClientWriteAttributes": [],
    "userpoolClientReadAttributes": [],
    "userpoolClientLambdaRole": "huppo3c2a37cc_userpoolclient_lambda_role",
    "userpoolClientSetAttributes": false,
    "sharedId": "3c2a37cc",
    "resourceName": "huppo",
    "authSelections": "identityPoolAndUserPool",
    "serviceName": "Cognito",
    "usernameAttributes": [
      "email"
    ],
    "useDefault": "manual",
    "userPoolGroups": false,
    "userPoolGroupList": [],
    "adminQueries": false,
    "thirdPartyAuth": false,
    "authProviders": [],
    "usernameCaseSensitive": false,
    "useEnabledMfas": true,
    "authRoleArn": {
      "Fn::GetAtt": [
        "AuthRole",
        "Arn"
      ]
    },
    "unauthRoleArn": {
      "Fn::GetAtt": [
        "UnauthRole",
        "Arn"
      ]
    },
    "breakCircularDependency": true,
    "dependsOn": [],
    "hostedUI": false
  }
}